connected_conics/__init__.py
connected_conics/conic.py
connected_conics/helpers.py
connected_conics/surf.py
connected_conics-0.0.3.dist-info/LICENSE.txt
connected_conics-0.0.3.dist-info/METADATA
connected_conics-0.0.3.dist-info/WHEEL
connected_conics-0.0.3.dist-info/top_level.txt
connected_conics-0.0.3.dist-info/RECORD
